pdbr/__init__.py
pdbr/__main__.py
pdbr/_cm.py
pdbr/_console_layout.py
pdbr/_pdbr.py
pdbr/cli.py
pdbr/helpers.py
pdbr/middlewares/__init__.py
pdbr/middlewares/django.py
pdbr/middlewares/starlette.py
pdbr/runner.py
pdbr/utils.py
pdbr-0.9.7.dist-info/METADATA
pdbr-0.9.7.dist-info/WHEEL
pdbr-0.9.7.dist-info/entry_points.txt
pdbr-0.9.7.dist-info/licenses/LICENSE
pdbr-0.9.7.dist-info/RECORD
