Metadata-Version: 2.4
Name: pdbr
Version: 0.9.7
Summary: Pdb with Rich library.
License-File: LICENSE
Author: Can Sarigol
Author-email: ertugrulsarigol@gmail.com
Requires-Python: >=3.7.9,<4.0.0
Classifier: Development Status :: 4 - Beta
Classifier: Intended Audience :: Developers
Classifier: Operating System :: MacOS
Classifier: Operating System :: Microsoft :: Windows
Classifier: Operating System :: POSIX :: Linux
Classifier: Programming Language :: Python :: 3
Classifier: Programming Language :: Python :: 3.8
Classifier: Programming Language :: Python :: 3.9
Classifier: Programming Language :: Python :: 3.10
Classifier: Programming Language :: Python :: 3.11
Classifier: Programming Language :: Python :: 3.12
Classifier: Programming Language :: Python :: 3.13
Classifier: Programming Language :: Python :: 3.14
Provides-Extra: ipython
Requires-Dist: ipython ; extra == "ipython"
Requires-Dist: pyreadline3 (>=3.4.1,<4.0.0) ; sys_platform == "win32"
Requires-Dist: rich
Project-URL: Homepage, https://github.com/cansarigol/pdbr
Project-URL: Repository, https://github.com/cansarigol/pdbr
